syntheseus/__init__.py
syntheseus/py.typed
syntheseus/cli/__init__.py
syntheseus/cli/eval_single_step.py
syntheseus/cli/main.py
syntheseus/cli/search.py
syntheseus/cli/search_config.yml
syntheseus/interface/__init__.py
syntheseus/interface/bag.py
syntheseus/interface/models.py
syntheseus/interface/molecule.py
syntheseus/interface/reaction.py
syntheseus/reaction_prediction/__init__.py
syntheseus/reaction_prediction/inference_base.py
syntheseus/reaction_prediction/chem/__init__.py
syntheseus/reaction_prediction/chem/utils.py
syntheseus/reaction_prediction/data/__init__.py
syntheseus/reaction_prediction/data/dataset.py
syntheseus/reaction_prediction/data/reaction_sample.py
syntheseus/reaction_prediction/environment_gln/Dockerfile
syntheseus/reaction_prediction/environment_gln/environment.yml
syntheseus/reaction_prediction/inference/__init__.py
syntheseus/reaction_prediction/inference/base.py
syntheseus/reaction_prediction/inference/chemformer.py
syntheseus/reaction_prediction/inference/config.py
syntheseus/reaction_prediction/inference/default_checkpoint_links.yml
syntheseus/reaction_prediction/inference/gln.py
syntheseus/reaction_prediction/inference/graph2edits.py
syntheseus/reaction_prediction/inference/local_retro.py
syntheseus/reaction_prediction/inference/megan.py
syntheseus/reaction_prediction/inference/mhnreact.py
syntheseus/reaction_prediction/inference/retro_knn.py
syntheseus/reaction_prediction/inference/root_aligned.py
syntheseus/reaction_prediction/inference/toy_models.py
syntheseus/reaction_prediction/models/__init__.py
syntheseus/reaction_prediction/models/retro_knn.py
syntheseus/reaction_prediction/utils/__init__.py
syntheseus/reaction_prediction/utils/config.py
syntheseus/reaction_prediction/utils/downloading.py
syntheseus/reaction_prediction/utils/inference.py
syntheseus/reaction_prediction/utils/metrics.py
syntheseus/reaction_prediction/utils/misc.py
syntheseus/reaction_prediction/utils/model_loading.py
syntheseus-0.7.1.dist-info/licenses/LICENSE
syntheseus-0.7.1.dist-info/METADATA
syntheseus-0.7.1.dist-info/WHEEL
syntheseus-0.7.1.dist-info/entry_points.txt
syntheseus-0.7.1.dist-info/top_level.txt
syntheseus-0.7.1.dist-info/RECORD
