Metadata-Version: 2.4
Name: syntheseus
Version: 0.7.1
Summary: A package for retrosynthetic planning.
Author: Austin Tripp, Krzysztof Maziarz, Guoqing Liu, Megan Stanley, Marwin Segler
License:     MIT License
Project-URL: Documentation, https://microsoft.github.io/syntheseus
Project-URL: Repository, https://github.com/microsoft/syntheseus
Requires-Python: >=3.8
License-File: LICENSE
Requires-Dist: more_itertools
Requires-Dist: networkx
Requires-Dist: numpy
Requires-Dist: omegaconf
Requires-Dist: rdkit
Requires-Dist: tqdm
Provides-Extra: viz
Requires-Dist: pillow; extra == "viz"
Requires-Dist: graphviz; extra == "viz"
Provides-Extra: dev
Requires-Dist: pytest; extra == "dev"
Requires-Dist: pytest-cov; extra == "dev"
Requires-Dist: pytest-rerunfailures; extra == "dev"
Requires-Dist: pre-commit; extra == "dev"
Provides-Extra: chemformer
Requires-Dist: syntheseus-chemformer==0.3.0; extra == "chemformer"
Provides-Extra: graph2edits
Requires-Dist: syntheseus-graph2edits==0.2.0; extra == "graph2edits"
Provides-Extra: local-retro
Requires-Dist: syntheseus-local-retro==0.5.0; extra == "local-retro"
Provides-Extra: megan
Requires-Dist: syntheseus-megan==0.2.0; extra == "megan"
Provides-Extra: mhn-react
Requires-Dist: syntheseus-mhnreact==1.0.0; extra == "mhn-react"
Provides-Extra: retro-knn
Requires-Dist: syntheseus[local-retro]; extra == "retro-knn"
Provides-Extra: root-aligned
Requires-Dist: syntheseus-root-aligned==0.2.0; extra == "root-aligned"
Provides-Extra: all-single-step
Requires-Dist: syntheseus[chemformer,graph2edits,local-retro,megan,mhn-react,retro-knn,root-aligned]; extra == "all-single-step"
Provides-Extra: all
Requires-Dist: syntheseus[all-single-step,dev,viz]; extra == "all"
Dynamic: license-file
